cicore/__init__.py
cicore/getPath.py
cicore/api/__init__.py
cicore-0.0.12.dist-info/METADATA
cicore-0.0.12.dist-info/WHEEL
cicore-0.0.12.dist-info/top_level.txt
cicore-0.0.12.dist-info/RECORD
