Metadata-Version: 2.4
Name: cicore
Version: 0.0.12
Summary: A core utility library for daily Python tasks.
Home-page: https://github.com/bilibili-dideng/
Author: 地灯dideng
Author-email: 3483434955@qq.com
Classifier: Programming Language :: Python :: 3
Classifier: License :: OSI Approved :: MIT License
Classifier: Operating System :: OS Independent
Classifier: Development Status :: 4 - Beta
Classifier: Intended Audience :: Developers
Requires-Python: >=3.6
Requires-Dist: wtfami
Requires-Dist: PyQt5
Requires-Dist: jsonschema
Requires-Dist: pyperclip
Requires-Dist: DidengAPI
Dynamic: author
Dynamic: author-email
Dynamic: classifier
Dynamic: description
Dynamic: description-content-type
Dynamic: home-page
Dynamic: requires-dist
Dynamic: requires-python
Dynamic: summary
